{
  "main": {
    "id": "de8d00f15f0cdf02",
    "type": "split",
    "children": [
      {
        "id": "c9f2b694c1e602e6",
        "type": "tabs",
        "children": [
          {
            "id": "4e1f45ed21cf9e97",
            "type": "leaf",
            "state": {
              "type": "markdown",
              "state": {
                "file": "Scribble Pad.md",
                "mode": "source",
                "source": false
              }
            }
          }
        ]
      }
    ],
    "direction": "vertical"
  },
  "left": {
    "id": "eb64a9d9f189af73",
    "type": "split",
    "children": [
      {
        "id": "78144263227ef63d",
        "type": "tabs",
        "children": [
          {
            "id": "389cb47c7ca71e29",
            "type": "leaf",
            "state": {
              "type": "file-explorer",
              "state": {
                "sortOrder": "alphabetical"
              }
            }
          },
          {
            "id": "31004747b041a49f",
            "type": "leaf",
            "state": {
              "type": "search",
              "state": {
                "query": "",
                "matchingCase": false,
                "explainSearch": false,
                "collapseAll": false,
                "extraContext": false,
                "sortOrder": "alphabetical"
              }
            }
          },
          {
            "id": "00abac0cbc542e48",
            "type": "leaf",
            "state": {
              "type": "bookmarks",
              "state": {}
            }
          }
        ]
      }
    ],
    "direction": "horizontal",
    "width": 250.5
  },
  "right": {
    "id": "0f6c58b54e314b16",
    "type": "split",
    "children": [
      {
        "id": "b21c496c1621cb69",
        "type": "tabs",
        "dimension": 33.397683397683394,
        "children": [
          {
            "id": "c4d94ef82c45a0e8",
            "type": "leaf",
            "state": {
              "type": "backlink",
              "state": {
                "file": "Scribble Pad.md",
                "collapseAll": true,
                "extraContext": false,
                "sortOrder": "alphabetical",
                "showSearch": false,
                "searchQuery": "",
                "backlinkCollapsed": true,
                "unlinkedCollapsed": true
              }
            }
          },
          {
            "id": "8917c10796700472",
            "type": "leaf",
            "state": {
              "type": "outgoing-link",
              "state": {
                "file": "Scribble Pad.md",
                "linksCollapsed": false,
                "unlinkedCollapsed": true
              }
            }
          },
          {
            "id": "3351e9644ca85845",
            "type": "leaf",
            "state": {
              "type": "tag",
              "state": {
                "sortOrder": "frequency",
                "useHierarchy": true
              }
            }
          },
          {
            "id": "d85e0fe360795559",
            "type": "leaf",
            "state": {
              "type": "outline",
              "state": {
                "file": "Scribble Pad.md"
              }
            }
          },
          {
            "id": "d4f33c6d68e02186",
            "type": "leaf",
            "state": {
              "type": "calendar",
              "state": {}
            }
          }
        ],
        "currentTab": 3
      },
      {
        "id": "2dca3c7765e2a50e",
        "type": "tabs",
        "dimension": 66.6023166023166,
        "children": [
          {
            "id": "bef5b8265cab87f1",
            "type": "leaf",
            "state": {
              "type": "timeline",
              "state": {}
            }
          }
        ]
      }
    ],
    "direction": "horizontal",
    "width": 300
  },
  "left-ribbon": {
    "hiddenItems": {
      "switcher:Open quick switcher": false,
      "graph:Open graph view": false,
      "canvas:Create new canvas": false,
      "daily-notes:Open today's daily note": false,
      "templates:Insert template": false,
      "command-palette:Open command palette": false,
      "obsidian-statusbar-pomo:Start pomodoro": false
    }
  },
  "active": "4e1f45ed21cf9e97",
  "lastOpenFiles": [
    "Untitled.md",
    "Day Planners/Day Planner-20230818.md",
    "Scribble Pad.md",
    "Kubernetes/Kubernetes Deployment.md",
    "Docker/Networking.md",
    "Day Planners/Day Planner-20230809.md",
    "questions.md",
    "Kubernetes/Networking/Internal Networking.md",
    "Untitled.canvas",
    "Pasted image 20230818151647.png",
    "Pasted image 20230818150110.png",
    "Pasted image 20230818113339.png",
    "Pasted image 20230818113259.png",
    "Pasted image 20230818111023.png",
    "Pasted image 20230818110938.png",
    "Pasted image 20230818105249.png",
    "Python Virtual Environments.md",
    "project ideas.md",
    "Kubernetes/Networking/Network Layers.md",
    "Kubernetes/Networking/MultiCluster Communication.md",
    "Kubernetes/Networking/ExternalDNS.md",
    "Kubernetes/Networking/External Networking.md",
    "Kubernetes/Networking/CoreDNS.md",
    "Kubernetes/Networking/Container Network Interface.md",
    "Git.md",
    "Kubernetes/Services.md",
    "Day Planners/Day Planner-20230814.md",
    "Day Planners/Day Planner-20230811.md",
    "Day Planners/Day Planner-20230813.md",
    "Cryptopals write up.md",
    "Pasted image 20230811114018.png",
    "Kubernetes/Pods.md",
    "Pasted image 20230811114000.png",
    "Pasted image 20230811113939.png",
    "2023-08-09.md",
    "Day Planners/Day Planner-20230810.md",
    "Day Planners",
    "Cloud",
    "Kubernetes/Networking/Container Network Interface",
    "Monitoring/Grafana",
    "Monitoring/Prometheus",
    "Monitoring",
    "Kubernetes/Networking",
    "Networking/Domain Name System (DNS)",
    "Networking/OSI Model",
    "Miscellaneous"
  ]
}